bitpay/__init__.py
bitpay/client.py
bitpay/exceptions.py
bitpay/key_utils.py
globee-2.3.3.dist-info/DESCRIPTION.rst
globee-2.3.3.dist-info/METADATA
globee-2.3.3.dist-info/RECORD
globee-2.3.3.dist-info/WHEEL
globee-2.3.3.dist-info/metadata.json
globee-2.3.3.dist-info/top_level.txt
