Metadata-Version: 2.0
Name: globee
Version: 2.3.3
Summary: Accept altcoins with GloBee
Home-page: https://github.com/GloBee-Official/bitpay-python
Author: GloBee Integrations Team
Author-email: integrations@globee.com
License: UNKNOWN
Download-URL: https://github.com/GloBee-Official/bitpay-python/tarball/v2.3.3
Keywords: bitcoin,payments,crypto,altcoins
Platform: UNKNOWN
Classifier: Programming Language :: Python :: 3.4
Classifier: Programming Language :: Python :: 3 :: Only
Classifier: Development Status :: 5 - Production/Stable
Classifier: Environment :: Web Environment
Classifier: Intended Audience :: Developers
Classifier: License :: OSI Approved :: MIT License
Classifier: Operating System :: OS Independent
Classifier: Topic :: Software Development :: Libraries :: Python Modules
Classifier: Topic :: Office/Business :: Financial
Requires-Dist: ecdsa
Requires-Dist: requests
